Metadata-Version: 2.1
Name: PandasXlFramer
Version: 0.1
Summary: PandasXlFramer
Home-page: https://github.com/TengGao/pandasxlframer
Author: Mike Gao
Author-email: tenggao@gmail.com
License: MIT
Project-URL: Repository, https://github.com/TengGao/pandasxlframer
Project-URL: Bug Reports, https://github.com/TengGao/pandasxlframer/issues
Keywords: pandasxlframer xlsx excel pandas formatter
Platform: UNKNOWN
Classifier: Development Status :: 2 - Pre-Alpha
Classifier: Intended Audience :: Developers
Classifier: License :: OSI Approved :: MIT License
Classifier: Topic :: Software Development :: Libraries :: Python Modules
Classifier: Programming Language :: Python :: 3
Classifier: Programming Language :: Python :: 3 :: Only
Classifier: Programming Language :: Python :: 3.6
Classifier: Programming Language :: Python :: 3.7
Classifier: Programming Language :: Python :: 3.8
Classifier: Programming Language :: Python :: 3.9
Requires-Python: >=3.6
